pywalker/__init__.py
pywalker-0.1.3.dist-info/METADATA
pywalker-0.1.3.dist-info/WHEEL
pywalker-0.1.3.dist-info/RECORD
