Metadata-Version: 2.4
Name: pywalker
Version: 0.1.3
Summary: A utility for discovering and importing Python modules in a package or directory.
Project-URL: homepage, https://github.com/eyueldk/pywalker
Project-URL: repository, https://github.com/eyueldk/pywalker
Author: eyueldk
License: MIT
Keywords: dynamic import,import,module discovery,python
Classifier: Intended Audience :: Developers
Classifier: License :: OSI Approved :: MIT License
Classifier: Operating System :: OS Independent
Classifier: Programming Language :: Python :: 3
Classifier: Programming Language :: Python :: 3.12
Classifier: Topic :: Software Development :: Libraries :: Python Modules
Requires-Python: >=3.9
